Metadata-Version: 1.0
Name: pymonaco
Version: 0.1
Summary: Load Monaco dose plane output files
Home-page: UNKNOWN
Author: Simon Biggs
Author-email: mail@simonbiggs.net
License: AGPL3+
Platform: UNKNOWN
